semantically/__init__.py
semantically/async_request.py
semantically/client.py
semantically/config.py
semantically/datastructures.py
semantically/exceptions.py
semantically/paper_list.py
semantically/request.py
semantically/response_codes.py
semantically/semantically.py
semantically-0.2.2.dist-info/LICENSE.md
semantically-0.2.2.dist-info/METADATA
semantically-0.2.2.dist-info/WHEEL
semantically-0.2.2.dist-info/top_level.txt
semantically-0.2.2.dist-info/RECORD
