Metadata-Version: 2.1
Name: semantically
Version: 0.2.2
Summary: Semantically is a Python library designed to easily retrieve data from Semantic Scholar.
Home-page: https://github.com/dev-89/semantically
Author: Kay Herklotz
Author-email: kay.herklotz@gmail.com
License: LICENSE.md
Project-URL: Bug Tracker, https://github.com/dev-89/semantically/issues
Platform: UNKNOWN
Requires-Python: >=3.6
License-File: LICENSE.md
Requires-Dist: aiohttp
Requires-Dist: Levenshtein
Requires-Dist: dacite
Requires-Dist: requests
Requires-Dist: pylint
Requires-Dist: black
